AUTHORS.rst
CONTRIBUTING.rst
HISTORY.rst
MANIFEST.in
README.rst
setup.cfg
setup.py
dbaas_cloudstack/__init__.py
dbaas_cloudstack/client.py
dbaas_cloudstack/models.py
dbaas_cloudstack/provider.py
dbaas_cloudstack.egg-info/PKG-INFO
dbaas_cloudstack.egg-info/SOURCES.txt
dbaas_cloudstack.egg-info/dependency_links.txt
dbaas_cloudstack.egg-info/not-zip-safe
dbaas_cloudstack.egg-info/requires.txt
dbaas_cloudstack.egg-info/top_level.txt
dbaas_cloudstack/admin/__init__.py
dbaas_cloudstack/admin/bundle_group.py
dbaas_cloudstack/admin/cloudstack_bundle.py
dbaas_cloudstack/admin/cloudstack_pack.py
dbaas_cloudstack/admin/cloudstack_region.py
dbaas_cloudstack/admin/cloudstack_serviceoffering.py
dbaas_cloudstack/admin/offering_group.py
dbaas_cloudstack/api/__init__.py
dbaas_cloudstack/api/urls.py
dbaas_cloudstack/api/views.py
dbaas_cloudstack/forms/__init__.py
dbaas_cloudstack/forms/cloudstack_bundle.py
dbaas_cloudstack/migrations/0001_initial.py
dbaas_cloudstack/migrations/0002_auto__add_field_databaseinfraattr_dns.py
dbaas_cloudstack/migrations/0003_auto__add_cloudstackoffering__add_cloudstackbundle__del_field_planattr.py
dbaas_cloudstack/migrations/0004_auto__add_lastusedbundle__add_unique_lastusedbundle_plan_bundle.py
dbaas_cloudstack/migrations/0005_auto__add_field_databaseinfraattr_networkapi_equipment_id__add_field_d.py
dbaas_cloudstack/migrations/0006_auto__add_databaseinfraoffering__add_cloudstackregion__add_field_cloud.py
dbaas_cloudstack/migrations/0007_auto__add_cloudstackpack__chg_field_cloudstackoffering_region__chg_fie.py
dbaas_cloudstack/migrations/0008_auto__add_field_cloudstackpack_name.py
dbaas_cloudstack/migrations/0009_auto__del_field_cloudstackpack_userdata__add_field_cloudstackpack_init.py
dbaas_cloudstack/migrations/0010_auto__del_field_cloudstackpack_is_ha__del_field_cloudstackpack_init_sc.py
dbaas_cloudstack/migrations/0011_auto__add_field_cloudstackoffering_equivalent_offering.py
dbaas_cloudstack/migrations/0012_auto__chg_field_cloudstackoffering_equivalent_offering.py
dbaas_cloudstack/migrations/0013_auto__add_field_cloudstackbundle_equivalent_bundle.py
dbaas_cloudstack/migrations/0014_auto__del_field_cloudstackbundle_equivalent_bundle.py
