Metadata-Version: 1.1
Name: dbaas-cloudstack
Version: 0.9.12
Summary: A cloudstack adapter to DBaaS
Home-page: https://github.com/globocom/dbaas-cloudstack
Author: Felippe da Motta Raposo
Author-email: raposo.felippe@gmail.com
License: BSD
Keywords: dbaas-cloudstack
Platform: UNKNOWN
Classifier: Development Status :: 2 - Pre-Alpha
Classifier: Framework :: Django
Classifier: Intended Audience :: Developers
Classifier: License :: OSI Approved :: BSD License
Classifier: Natural Language :: English
Classifier: Programming Language :: Python :: 2
Classifier: Programming Language :: Python :: 2.6
Classifier: Programming Language :: Python :: 2.7
Classifier: Programming Language :: Python :: 3
Classifier: Programming Language :: Python :: 3.3
